setup.py
zdq_test/__init__.py
zdq_test.egg-info/PKG-INFO
zdq_test.egg-info/SOURCES.txt
zdq_test.egg-info/dependency_links.txt
zdq_test.egg-info/top_level.txt