Metadata-Version: 1.0
Name: zdq-test
Version: 0.0.1
Summary: a python json serialize/deserialize library which is easy to use
Home-page: UNKNOWN
Author: zhoudeqiang
Author-email: zhoudeqiang@outlook.com
License: MIT License
Keywords: zdq_test
Platform: any
